adt/__init__.py
adt/adt.py
python_adt-0.0.0.dist-info/AUTHORS.rst
python_adt-0.0.0.dist-info/LICENSE
python_adt-0.0.0.dist-info/METADATA
python_adt-0.0.0.dist-info/WHEEL
python_adt-0.0.0.dist-info/top_level.txt
python_adt-0.0.0.dist-info/RECORD
