Metadata-Version: 2.1
Name: python-adt
Version: 0.0.0
Summary: Implementation of advanced data structure
Home-page: https://github.com/benzid-wael/adt
Author: Wael Ben Zid
Author-email: benzid.wael@hotmail.fr
License: GNU General Public License v3
Keywords: adt
Platform: UNKNOWN
Classifier: Development Status :: 2 - Pre-Alpha
Classifier: Intended Audience :: Developers
Classifier: License :: OSI Approved :: GNU General Public License v3 (GPLv3)
Classifier: Natural Language :: English
Classifier: Programming Language :: Python :: 3
Classifier: Programming Language :: Python :: 3.5
Classifier: Programming Language :: Python :: 3.6
Classifier: Programming Language :: Python :: 3.7
Classifier: Programming Language :: Python :: 3.8
Requires-Python: >=3.5
